submail/__init__.py
submail/common.py
submail/mail.py
submail/sms.py
submail/submail.py
submail-0.4.dist-info/DESCRIPTION.rst
submail-0.4.dist-info/METADATA
submail-0.4.dist-info/RECORD
submail-0.4.dist-info/WHEEL
submail-0.4.dist-info/metadata.json
submail-0.4.dist-info/top_level.txt
tests/__init__.py
tests/test_mail.py
tests/test_message.py
