Metadata-Version: 2.0
Name: submail
Version: 0.4
Summary: submail sdk
Home-page: https://github.com/free-free/submail
Author: HuangBiao
Author-email: 19941222hb@gmail.com
License: MIT
Keywords: submail,sdk
Platform: UNKNOWN
Classifier: Intended Audience :: Developers
Classifier: License :: OSI Approved :: MIT License
Classifier: Programming Language :: Python
Classifier: Programming Language :: Python :: 3
Classifier: Programming Language :: Python :: 3.3
Classifier: Programming Language :: Python :: 3.4
Classifier: Programming Language :: Python :: 3.5
Classifier: Topic :: Software Development :: Libraries :: Python Modules
Classifier: Topic :: Internet :: WWW/HTTP :: Dynamic Content
Requires-Dist: pytest
Requires-Dist: requests
